banrep/__init__.py
banrep/__version__.py
banrep/extraccion.py
banrep/io.py
banrep/linguistica.py
banrep/preprocesos.py
banrep/tabulados.py
banrep/transforma.py
banrep/tests/__init__.py
banrep/tests/test_extraccion.py
banrep/tests/test_io.py
banrep/tests/test_preprocesos.py
banrep/tests/test_utils.py
banrep-6.0.2.dist-info/LICENSE
banrep-6.0.2.dist-info/METADATA
banrep-6.0.2.dist-info/WHEEL
banrep-6.0.2.dist-info/top_level.txt
banrep-6.0.2.dist-info/RECORD
