Metadata-Version: 2.1
Name: banrep
Version: 6.0.2
Summary: Analítica de Texto en el Banco de la República
Home-page: https://github.com/munozbravo/banrep
Author: Germán Muñoz
Author-email: gamunozbravo@gmail.com
License: UNKNOWN
Platform: UNKNOWN
Classifier: License :: OSI Approved :: MIT License
Classifier: Natural Language :: Spanish
Classifier: Operating System :: OS Independent
Classifier: Programming Language :: Python :: 3.7
Requires-Python: ~=3.7
Requires-Dist: gensim (>=3.8)
Requires-Dist: pandas (>=1.0)
Requires-Dist: spacy (<3.0,>=2.2)
Requires-Dist: tika (>=1.19)
Requires-Dist: lxml (>=4.5)
Requires-Dist: xlrd (==1.2)
